tspq0.py
tspq0-0.1.24.dist-info/LICENSE
tspq0-0.1.24.dist-info/METADATA
tspq0-0.1.24.dist-info/WHEEL
tspq0-0.1.24.dist-info/top_level.txt
tspq0-0.1.24.dist-info/RECORD
