Metadata-Version: 2.1
Name: tspq0
Version: 0.1.24
Summary: Travelling salesman problem by qiskit
Home-page: UNKNOWN
Author: Mars Mel
License: UNKNOWN
Platform: UNKNOWN
License-File: LICENSE
Requires-Dist: Jinja2 (==3.1.2)
Requires-Dist: MarkupSafe (==2.1.1)
Requires-Dist: Pillow (==9.3.0)
Requires-Dist: PyYAML (==6.0)
Requires-Dist: Pygments (==2.13.0)
Requires-Dist: QtPy (==2.3.0)
Requires-Dist: Send2Trash (==1.8.0)
Requires-Dist: anyio (==3.6.2)
Requires-Dist: argon2-cffi-bindings (==21.2.0)
Requires-Dist: argon2-cffi (==21.3.0)
Requires-Dist: arrow (==1.2.3)
Requires-Dist: asttokens (==2.2.1)
Requires-Dist: attrs (==22.1.0)
Requires-Dist: backcall (==0.2.0)
Requires-Dist: beautifulsoup4 (==4.11.1)
Requires-Dist: bleach (==5.0.1)
Requires-Dist: certifi (==2022.12.7)
Requires-Dist: cffi (==1.15.1)
Requires-Dist: charset-normalizer (==2.1.1)
Requires-Dist: comm (==0.1.2)
Requires-Dist: contourpy (==1.0.6)
Requires-Dist: cryptography (==38.0.4)
Requires-Dist: cycler (==0.11.0)
Requires-Dist: debugpy (==1.6.4)
Requires-Dist: decorator (==5.1.1)
Requires-Dist: defusedxml (==0.7.1)
Requires-Dist: dill (==0.3.6)
Requires-Dist: docplex (==2.24.232)
Requires-Dist: entrypoints (==0.4)
Requires-Dist: executing (==1.2.0)
Requires-Dist: fastjsonschema (==2.16.2)
Requires-Dist: fonttools (==4.38.0)
Requires-Dist: fqdn (==1.5.1)
Requires-Dist: idna (==3.4)
Requires-Dist: ipykernel (==6.19.2)
Requires-Dist: ipython-genutils (==0.2.0)
Requires-Dist: ipython (==8.7.0)
Requires-Dist: ipywidgets (==8.0.3)
Requires-Dist: isoduration (==20.11.0)
Requires-Dist: jedi (==0.18.2)
Requires-Dist: jsonpointer (==2.3)
Requires-Dist: jsonschema (==4.17.3)
Requires-Dist: jupyter-console (==6.4.4)
Requires-Dist: jupyter-events (==0.5.0)
Requires-Dist: jupyter (==1.0.0)
Requires-Dist: jupyter-client (==7.4.8)
Requires-Dist: jupyter-core (==5.1.0)
Requires-Dist: jupyter-server (==2.0.1)
Requires-Dist: jupyter-server-terminals (==0.4.2)
Requires-Dist: jupyterlab-pygments (==0.2.2)
Requires-Dist: jupyterlab-widgets (==3.0.4)
Requires-Dist: kiwisolver (==1.4.4)
Requires-Dist: matplotlib-inline (==0.1.6)
Requires-Dist: matplotlib (==3.6.2)
Requires-Dist: mistune (==2.0.4)
Requires-Dist: mpmath (==1.2.1)
Requires-Dist: nbclassic (==0.4.8)
Requires-Dist: nbclient (==0.7.2)
Requires-Dist: nbconvert (==7.2.6)
Requires-Dist: nbformat (==5.7.0)
Requires-Dist: nest-asyncio (==1.5.6)
Requires-Dist: networkx (==2.8.8)
Requires-Dist: notebook (==6.5.2)
Requires-Dist: notebook-shim (==0.2.2)
Requires-Dist: ntlm-auth (==1.5.0)
Requires-Dist: numpy (==1.23.5)
Requires-Dist: packaging (==22.0)
Requires-Dist: pandas (==1.5.2)
Requires-Dist: pandocfilters (==1.5.0)
Requires-Dist: parso (==0.8.3)
Requires-Dist: pbr (==5.11.0)
Requires-Dist: pexpect (==4.8.0)
Requires-Dist: pickleshare (==0.7.5)
Requires-Dist: platformdirs (==2.6.0)
Requires-Dist: ply (==3.11)
Requires-Dist: prometheus-client (==0.15.0)
Requires-Dist: prompt-toolkit (==3.0.36)
Requires-Dist: psutil (==5.9.4)
Requires-Dist: ptyprocess (==0.7.0)
Requires-Dist: pure-eval (==0.2.2)
Requires-Dist: pycparser (==2.21)
Requires-Dist: pydot (==1.4.2)
Requires-Dist: pylatexenc (==2.10)
Requires-Dist: pyparsing (==3.0.9)
Requires-Dist: pyrsistent (==0.19.2)
Requires-Dist: python-dateutil (==2.8.2)
Requires-Dist: python-json-logger (==2.0.4)
Requires-Dist: pytz (==2022.6)
Requires-Dist: pyzmq (==24.0.1)
Requires-Dist: qiskit-aer-gpu (==0.11.2)
Requires-Dist: qiskit-aer (==0.11.2)
Requires-Dist: qiskit-ibmq-provider (==0.19.2)
Requires-Dist: qiskit-optimization (==0.4.0)
Requires-Dist: qiskit-terra (==0.22.3)
Requires-Dist: qiskit (==0.39.4)
Requires-Dist: qtconsole (==5.4.0)
Requires-Dist: requests-ntlm (==1.1.0)
Requires-Dist: requests (==2.28.1)
Requires-Dist: retworkx (==0.12.1)
Requires-Dist: rfc3339-validator (==0.1.4)
Requires-Dist: rfc3986-validator (==0.1.1)
Requires-Dist: rustworkx (==0.12.1)
Requires-Dist: scipy (==1.9.3)
Requires-Dist: seaborn (==0.12.1)
Requires-Dist: six (==1.16.0)
Requires-Dist: sniffio (==1.3.0)
Requires-Dist: soupsieve (==2.3.2.post1)
Requires-Dist: stack-data (==0.6.2)
Requires-Dist: stevedore (==4.1.1)
Requires-Dist: symengine (==0.9.2)
Requires-Dist: sympy (==1.11.1)
Requires-Dist: terminado (==0.17.1)
Requires-Dist: tinycss2 (==1.2.1)
Requires-Dist: tornado (==6.2)
Requires-Dist: traitlets (==5.7.0)
Requires-Dist: tweedledum (==1.1.1)
Requires-Dist: uri-template (==1.2.0)
Requires-Dist: urllib3 (==1.26.13)
Requires-Dist: wcwidth (==0.2.5)
Requires-Dist: webcolors (==1.12)
Requires-Dist: webencodings (==0.5.1)
Requires-Dist: websocket-client (==1.4.2)
Requires-Dist: websockets (==10.4)
Requires-Dist: widgetsnbextension (==4.0.4)
